pycanarytoken_lib/__init__.py
pycanarytoken_lib/core.py
pycanarytoken-0.1.1.dist-info/METADATA
pycanarytoken-0.1.1.dist-info/WHEEL
pycanarytoken-0.1.1.dist-info/entry_points.txt
pycanarytoken-0.1.1.dist-info/top_level.txt
pycanarytoken-0.1.1.dist-info/RECORD
